{"zoom": 1, "node_charge": -45, "node_gravity": 0.05, "link_distance": 15, "link_distance_variation": 0, "node_collision": true, "wiggle_nodes": false, "freeze_nodes": false, "node_fill_color": "#79aaa0", "node_stroke_color": "#555555", "node_label_color": "#000000", "display_node_labels": false, "scale_node_size_by_strength": false, "node_size": 5, "node_stroke_width": 1, "node_size_variation": 0.5, "link_color": "#7c7c7c", "link_width": 2, "link_alpha": 0.5, "link_width_variation": 0.5, "display_singleton_nodes": true, "min_link_weight_percentile": 0, "max_link_weight_percentile": 1}